nids_transformers/CORPUS.txt
nids_transformers/KMEANS-CLUSTER-CENTERS.npy
nids_transformers/NIDSTransformers.py
nids_transformers/SCALER.pkl
nids_transformers/TAGS-NAMES-EMBEDDINGS.npy
nids_transformers/__init__.py
nids_transformers-0.1.2.dist-info/METADATA
nids_transformers-0.1.2.dist-info/WHEEL
nids_transformers-0.1.2.dist-info/top_level.txt
nids_transformers-0.1.2.dist-info/RECORD
